README.md
setup.cfg
setup.py
freshtasks/__init__.py
freshtasks/api.py
freshtasks/task.py
freshtasks/task_utils.py
freshtasks.egg-info/PKG-INFO
freshtasks.egg-info/SOURCES.txt
freshtasks.egg-info/dependency_links.txt
freshtasks.egg-info/requires.txt
freshtasks.egg-info/top_level.txt
freshtasks/utils/__init__.py
freshtasks/utils/constants.py
freshtasks/utils/helper.py
tests/__init__.py
tests/test_api.py
tests/test_helper.py
tests/test_task_utils.py